syncmodels/__init__.py
syncmodels/context.py
syncmodels/crawler.py
syncmodels/crud.py
syncmodels/definitions.py
syncmodels/exceptions.py
syncmodels/geofactory.py
syncmodels/http.py
syncmodels/parallel.py
syncmodels/registry.py
syncmodels/requests.py
syncmodels/runner.py
syncmodels/schema.py
syncmodels/storage.py
syncmodels/syncmodels.py
syncmodels/timequeue.py
syncmodels/wave.py
syncmodels/auth/__init__.py
syncmodels/auth/basic.py
syncmodels/cli/__init__.py
syncmodels/cli/config.py
syncmodels/cli/main.py
syncmodels/cli/surreal.py
syncmodels/cli/wingdbstub.py
syncmodels/cli/workspace.py
syncmodels/helpers/__init__.py
syncmodels/helpers/crawler.py
syncmodels/helpers/explorer.py
syncmodels/helpers/faker.py
syncmodels/helpers/general.py
syncmodels/helpers/geojson.py
syncmodels/helpers/importers.py
syncmodels/helpers/loaders.py
syncmodels/helpers/models.py
syncmodels/helpers/orion.py
syncmodels/helpers/surreal.py
syncmodels/helpers/units.py
syncmodels/logic/__init__.py
syncmodels/logic/activity_logger.py
syncmodels/logic/analyzer.py
syncmodels/logic/browser.py
syncmodels/logic/swarm.py
syncmodels/logic/tasks.py
syncmodels/mapper/__init__.py
syncmodels/mapper/fiware.py
syncmodels/mapper/mapper.py
syncmodels/model/__init__.py
syncmodels/model/activity.py
syncmodels/model/geofilters.py
syncmodels/model/geojson.py
syncmodels/model/model.py
syncmodels/model/swarm.py
syncmodels/model/schema_org/__init__.py
syncmodels/model/schema_org/aboutpage.py
syncmodels/model/schema_org/action.py
syncmodels/model/schema_org/actionstatustype.py
syncmodels/model/schema_org/administrativearea.py
syncmodels/model/schema_org/adultorientedenumeration.py
syncmodels/model/schema_org/aggregateoffer.py
syncmodels/model/schema_org/aggregaterating.py
syncmodels/model/schema_org/alignmentobject.py
syncmodels/model/schema_org/anatomicalstructure.py
syncmodels/model/schema_org/anatomicalsystem.py
syncmodels/model/schema_org/article.py
syncmodels/model/schema_org/audience.py
syncmodels-0.1.357.dist-info/AUTHORS.rst
syncmodels-0.1.357.dist-info/LICENSE
syncmodels-0.1.357.dist-info/METADATA
syncmodels-0.1.357.dist-info/WHEEL
syncmodels-0.1.357.dist-info/entry_points.txt
syncmodels-0.1.357.dist-info/top_level.txt
syncmodels-0.1.357.dist-info/RECORD
